nqlstore/__init__.py
nqlstore/_base.py
nqlstore/_compat.py
nqlstore/_field.py
nqlstore/_mongo.py
nqlstore/_redis.py
nqlstore/_sql.py
nqlstore/query/__init__.py
nqlstore/query/parsers.py
nqlstore/query/selectors.py
nqlstore-0.2.0.dist-info/licenses/LICENSE
nqlstore-0.2.0.dist-info/METADATA
nqlstore-0.2.0.dist-info/WHEEL
nqlstore-0.2.0.dist-info/top_level.txt
nqlstore-0.2.0.dist-info/RECORD
