Metadata-Version: 2.4
Name: nqlstore
Version: 0.2.0
Summary: NQLStore, a simple CRUD store python library for `any query launguage` (or in short `nql`).
Author-email: Martin Ahindura <sales@sopherapps.com>
License: MIT License
Project-URL: Homepage, https://github.com/sopherapps/nqlstore
Project-URL: Repository, https://github.com/sopherapps/nqlstore
Project-URL: Documentation, https://github.com/sopherapps/nqlstore
Project-URL: Issues, https://github.com/sopherapps/nqlstore/issues
Project-URL: Changelog, https://github.com/sopherapps/nqlstore/blob/master/CHANGELOG.md
Keywords: database,model,orm
Classifier: Programming Language :: Python :: 3
Requires-Python: >=3.10
License-File: LICENSE
Requires-Dist: pydantic~=2.10.6
Provides-Extra: test
Requires-Dist: pytest~=8.3.4; extra == "test"
Requires-Dist: pytest-asyncio~=0.25.2; extra == "test"
Requires-Dist: isort~=5.13.2; extra == "test"
Requires-Dist: black~=24.10.0; extra == "test"
Provides-Extra: sql
Requires-Dist: sqlmodel~=0.0.22; extra == "sql"
Requires-Dist: aiosqlite~=0.20.0; extra == "sql"
Requires-Dist: greenlet~=3.1.1; extra == "sql"
Provides-Extra: mongo
Requires-Dist: beanie~=1.29.0; extra == "mongo"
Provides-Extra: redis
Requires-Dist: redis-om<0.3.4,~=0.3.3; extra == "redis"
Provides-Extra: all
Requires-Dist: sqlmodel~=0.0.22; extra == "all"
Requires-Dist: aiosqlite~=0.20.0; extra == "all"
Requires-Dist: greenlet~=3.1.1; extra == "all"
Requires-Dist: beanie~=1.29.0; extra == "all"
Requires-Dist: redis-om<0.3.4,~=0.3.3; extra == "all"
Dynamic: license-file
